robdupont/__init__.py
robdupont/sftp/__init__.py
robdupont/sftp/fake_ssh_keys
robdupont/sftp/sftp.py
robdupont-1.0.0.dist-info/METADATA
robdupont-1.0.0.dist-info/WHEEL
robdupont-1.0.0.dist-info/top_level.txt
robdupont-1.0.0.dist-info/RECORD
