Metadata-Version: 2.1
Name: robdupont
Version: 1.0.0
Summary: Utils content
Home-page: UNKNOWN
Author: Robin Dupont
License: MIT
Platform: UNKNOWN
Requires-Dist: pysftp
